./.gitignore
./PKG-INFO
./README.md
./pyproject.toml
./mp_scrape_source_nrw/__init__.py
mp_scrape_source_nrw-0.1.0.dist-info/METADATA
mp_scrape_source_nrw-0.1.0.dist-info/WHEEL
mp_scrape_source_nrw-0.1.0.dist-info/RECORD
